libcharm.cpython-39-x86_64-linux-gnu.so
CharmFeatures/LocalConfig.py
CharmFeatures/ProcessImages.py
CharmFeatures/__init__.py
CharmFeatures/_git_hash.py
CharmFeatures/_lib_version.py
CharmFeatures/_version.py
charmfeatures.libs/libfftw3-6b983104.so.3.5.5
charmfeatures.libs/libjbig-2504a0c3.so.2.1
charmfeatures.libs/libjpeg-e87d2658.so.62.2.0
charmfeatures.libs/libtiff-70e1437f.so.5.3.0
libcharm/_lib_version.py
libcharm/src/FeatureAlgorithms.cpp
libcharm/src/FeatureAlgorithms.h
libcharm/src/FeatureNames.cpp
libcharm/src/FeatureNames.h
libcharm/src/ImageTransforms.cpp
libcharm/src/ImageTransforms.h
libcharm/src/OldFeatureNamesFileStr.h
libcharm/src/Tasks.cpp
libcharm/src/Tasks.h
libcharm/src/VERSION
libcharm/src/capi.cpp
libcharm/src/cmatrix.cpp
libcharm/src/cmatrix.h
libcharm/src/libcharm.cpp
libcharm/src/libcharm.h
libcharm/src/Eigen/Cholesky
libcharm/src/Eigen/CholmodSupport
libcharm/src/Eigen/Core
libcharm/src/Eigen/Dense
libcharm/src/Eigen/Eigen
libcharm/src/Eigen/Eigenvalues
libcharm/src/Eigen/Geometry
libcharm/src/Eigen/Householder
libcharm/src/Eigen/IterativeLinearSolvers
libcharm/src/Eigen/Jacobi
libcharm/src/Eigen/KLUSupport
libcharm/src/Eigen/LU
libcharm/src/Eigen/MetisSupport
libcharm/src/Eigen/OrderingMethods
libcharm/src/Eigen/PaStiXSupport
libcharm/src/Eigen/PardisoSupport
libcharm/src/Eigen/QR
libcharm/src/Eigen/QtAlignedMalloc
libcharm/src/Eigen/SPQRSupport
libcharm/src/Eigen/SVD
libcharm/src/Eigen/Sparse
libcharm/src/Eigen/SparseCholesky
libcharm/src/Eigen/SparseCore
libcharm/src/Eigen/SparseLU
libcharm/src/Eigen/SparseQR
libcharm/src/Eigen/StdDeque
libcharm/src/Eigen/StdList
libcharm/src/Eigen/StdVector
libcharm/src/Eigen/SuperLUSupport
libcharm/src/Eigen/UmfPackSupport
libcharm/src/Eigen/src/Cholesky/LDLT.h
libcharm/src/Eigen/src/Cholesky/LLT.h
libcharm/src/Eigen/src/Cholesky/LLT_LAPACKE.h
libcharm/src/Eigen/src/CholmodSupport/CholmodSupport.h
charmfeatures-1.2.0.dist-info/METADATA
charmfeatures-1.2.0.dist-info/WHEEL
charmfeatures-1.2.0.dist-info/entry_points.txt
charmfeatures-1.2.0.dist-info/top_level.txt
charmfeatures-1.2.0.dist-info/RECORD
charmfeatures-1.2.0.dist-info/licenses/LICENSE.txt
charmfeatures-1.2.0.dist-info/sboms/auditwheel.cdx.json
