Metadata-Version: 2.1
Name: CharmFeatures
Version: 1.2.0
Summary: An image feature extraction library for python based on WND-CHARM
Home-page: https://gitlab.com/iggman/charm-features
Author: Ilya Goldberg, Nikita Orlov, Josiah Johnston, Lior Shamir, Chris Coletta
Author-email: igg <at> iggtec <dot> com
License: LGPLv2
Requires-Python: >=3.9
License-File: LICENSE.txt
Requires-Dist: numpy<2
Requires-Dist: scipy
Requires-Dist: tables
Requires-Dist: pylibtiff==0.6.1
Requires-Dist: fasteners
Requires-Dist: bitarray
Provides-Extra: test
Requires-Dist: pytest; extra == "test"
Requires-Dist: boto3; extra == "test"
Requires-Dist: botocore; extra == "test"
